purpleml/__init__.py
purpleml/correlation/base.py
purpleml/correlation/visualization.py
purpleml/sklearn/experiments/default.py
purpleml/sklearn/experiments/utils.py
purpleml/sklearn/model_selection/__init__.py
purpleml/sklearn/model_selection/_split.py
purpleml/sklearn/model_selection/_split_cross_split_search.py
purpleml/sklearn/model_selection/validation/cross_validate.py
purpleml/stats/univariate.py
purpleml/utils/context.py
purpleml/utils/dicts.py
purpleml/utils/misc.py
purpleml/utils/parallelization.py
purpleml/utils/timer.py
purpleml/visualization/network.py
purpleml-0.2.0.dist-info/LICENSE.txt
purpleml-0.2.0.dist-info/METADATA
purpleml-0.2.0.dist-info/WHEEL
purpleml-0.2.0.dist-info/top_level.txt
purpleml-0.2.0.dist-info/RECORD
