Metadata-Version: 2.1
Name: purpleml
Version: 0.2.0
Summary: Collection of tools for everyday machine learning and data science tasks
Home-page: https://github.com/pyscaffold/pyscaffold/
Author: Martin Becker
Author-email: mgbckr@stanford.edu
License: MIT
Project-URL: Documentation, https://pyscaffold.org/
Platform: any
Classifier: Development Status :: 4 - Beta
Classifier: Programming Language :: Python
License-File: LICENSE.txt
Requires-Dist: pandas
Requires-Dist: scikit-learn
Requires-Dist: statsmodels
Requires-Dist: mlflowhelper (>=1.2.0)
Requires-Dist: matplotlib
Requires-Dist: networkx
Requires-Dist: importlib-metadata ; python_version < "3.8"
Provides-Extra: testing
Requires-Dist: setuptools ; extra == 'testing'
Requires-Dist: pytest ; extra == 'testing'
Requires-Dist: pytest-cov ; extra == 'testing'
